{
  "$schema": "http://cyclonedx.org/schema/bom-1.4.schema.json",
  "bomFormat": "CycloneDX",
  "specVersion": "1.4",
  "serialNumber": "urn:uuid:cc6d035d-be91-4d77-8c04-f28a28adc313",
  "version": 1,
  "metadata": {
    "timestamp": "2024-01-05T19:08:22.381200+00:00",
    "tools": [
      {
        "vendor": "CycloneDX",
        "name": "cyclonedx-bom",
        "version": "3.11.7"
      },
      {
        "vendor": "CycloneDX",
        "name": "cyclonedx-python-lib",
        "version": "3.1.5",
        "externalReferences": [
          {
            "url": "https://github.com/CycloneDX/cyclonedx-python-lib/actions",
            "type": "build-system"
          },
          {
            "url": "https://pypi.org/project/cyclonedx-python-lib/",
            "type": "distribution"
          },
          {
            "url": "https://cyclonedx.github.io/cyclonedx-python-lib/",
            "type": "documentation"
          },
          {
            "url": "https://github.com/CycloneDX/cyclonedx-python-lib/issues",
            "type": "issue-tracker"
          },
          {
            "url": "https://github.com/CycloneDX/cyclonedx-python-lib/blob/main/LICENSE",
            "type": "license"
          },
          {
            "url": "https://github.com/CycloneDX/cyclonedx-python-lib/blob/main/CHANGELOG.md",
            "type": "release-notes"
          },
          {
            "url": "https://github.com/CycloneDX/cyclonedx-python-lib",
            "type": "vcs"
          },
          {
            "url": "https://cyclonedx.org",
            "type": "website"
          }
        ]
      }
    ]
  },
  "components": [
    {
      "type": "library",
      "bom-ref": "c5fca5e7-9d37-4a54-9fe9-59c5ccd149c2",
      "name": "PyYAML",
      "version": "6.0.1",
      "purl": "pkg:pypi/pyyaml@6.0.1"
    },
    {
      "type": "library",
      "bom-ref": "0fa60116-c1b5-49d5-9a1e-ef998ac1aad6",
      "name": "first",
      "version": "2.0.2",
      "purl": "pkg:pypi/first@2.0.2"
    },
    {
      "type": "library",
      "bom-ref": "c6d67faa-427f-4c5b-9e54-f9d8eacad6f7",
      "name": "jmespath",
      "version": "1.0.1",
      "purl": "pkg:pypi/jmespath@1.0.1"
    },
    {
      "type": "library",
      "bom-ref": "3b4f635a-3020-4978-98b6-f19c91488d36",
      "name": "jsonschema",
      "version": "4.20.0",
      "purl": "pkg:pypi/jsonschema@4.20.0"
    },
    {
      "type": "library",
      "bom-ref": "5dd5b284-0730-454a-b72c-95b2de564157",
      "name": "lxml",
      "version": "5.0.0",
      "purl": "pkg:pypi/lxml@5.0.0"
    },
    {
      "type": "library",
      "bom-ref": "8c0868cb-d085-4637-8451-c1c1def41509",
      "name": "msgspec",
      "version": "0.18.5",
      "purl": "pkg:pypi/msgspec@0.18.5"
    },
    {
      "type": "library",
      "bom-ref": "69711504-3ccf-4993-bcfd-235cedc929b3",
      "name": "referencing",
      "version": "0.32.1",
      "purl": "pkg:pypi/referencing@0.32.1"
    },
    {
      "type": "library",
      "bom-ref": "129cb820-d361-4db3-ac9c-7315914d35f0",
      "name": "toml",
      "version": "0.10.2",
      "purl": "pkg:pypi/toml@0.10.2"
    },
    {
      "type": "library",
      "bom-ref": "b50b23b0-c11b-4b52-87c2-9b602313517d",
      "name": "typer",
      "version": "0.9.0",
      "purl": "pkg:pypi/typer@0.9.0"
    },
    {
      "type": "library",
      "bom-ref": "a9304982-9438-4e29-b881-ba80eb852e75",
      "name": "xmlschema",
      "version": "2.5.1",
      "purl": "pkg:pypi/xmlschema@2.5.1"
    }
  ],
  "dependencies": [
    {
      "ref": "c5fca5e7-9d37-4a54-9fe9-59c5ccd149c2",
      "dependsOn": []
    },
    {
      "ref": "0fa60116-c1b5-49d5-9a1e-ef998ac1aad6",
      "dependsOn": []
    },
    {
      "ref": "c6d67faa-427f-4c5b-9e54-f9d8eacad6f7",
      "dependsOn": []
    },
    {
      "ref": "3b4f635a-3020-4978-98b6-f19c91488d36",
      "dependsOn": []
    },
    {
      "ref": "5dd5b284-0730-454a-b72c-95b2de564157",
      "dependsOn": []
    },
    {
      "ref": "8c0868cb-d085-4637-8451-c1c1def41509",
      "dependsOn": []
    },
    {
      "ref": "69711504-3ccf-4993-bcfd-235cedc929b3",
      "dependsOn": []
    },
    {
      "ref": "129cb820-d361-4db3-ac9c-7315914d35f0",
      "dependsOn": []
    },
    {
      "ref": "b50b23b0-c11b-4b52-87c2-9b602313517d",
      "dependsOn": []
    },
    {
      "ref": "a9304982-9438-4e29-b881-ba80eb852e75",
      "dependsOn": []
    }
  ]
}
